{
    "Base": {
        "time": 300,
        "optimal": false,
        "obj": "N/A",
        "sol": []
    },
    "Implied": {
        "time": 300,
        "optimal": false,
        "obj": "N/A",
        "sol": []
    },
    "Implied_Symmetry_On_Sizes": {
        "time": 300,
        "optimal": false,
        "obj": "N/A",
        "sol": []
    },
    "Implied_Symmetry_On_Distances": {
        "time": 300,
        "optimal": false,
        "obj": "N/A",
        "sol": []
    },
    "Implied_Symmetry": {
        "time": 300,
        "optimal": false,
        "obj": "N/A",
        "sol": []
    },
    "Symmetry": {
        "time": 300,
        "optimal": false,
        "obj": "N/A",
        "sol": []
    },
    "Two_Solvers_Base": {
        "time": 300,
        "optimal": false,
        "obj": 1574,
        "sol": [
            [
                20,
                5,
                26,
                17,
                40,
                21,
                34,
                10,
                19,
                33,
                29,
                27,
                30,
                25,
                22,
                6,
                4,
                32,
                15,
                12,
                28,
                7,
                31
            ],
            [
                23,
                41,
                36,
                35,
                47,
                43,
                42,
                37,
                45,
                46,
                39,
                38
            ],
            [
                16,
                18,
                1,
                11,
                2,
                13,
                14,
                44,
                3,
                24,
                8,
                9
            ]
        ]
    },
    "Two_Solvers_Implied": {
        "time": 300,
        "optimal": false,
        "obj": 1104,
        "sol": [
            [
                36,
                28,
                31,
                25,
                18,
                30,
                26,
                37,
                27,
                3,
                2,
                29,
                20,
                32,
                23,
                22,
                35,
                21,
                24,
                34
            ],
            [
                45,
                44,
                39,
                41,
                19,
                33,
                47,
                1,
                38,
                40,
                42,
                46,
                43
            ],
            [
                10,
                6,
                7,
                14,
                13,
                15,
                9,
                11,
                16,
                12,
                17,
                8,
                4,
                5
            ]
        ]
    },
    "Two_Solvers_Implied_Symmetry_On_Sizes": {
        "time": 300,
        "optimal": false,
        "obj": 1068,
        "sol": [
            [
                32,
                22,
                27,
                3,
                16,
                13,
                26,
                31,
                15,
                1,
                33,
                20,
                10,
                35,
                43,
                21
            ],
            [
                44,
                46,
                36,
                40,
                8,
                47,
                39,
                38,
                41,
                6,
                42,
                45,
                37,
                28
            ],
            [
                23,
                18,
                5,
                14,
                19,
                9,
                12,
                30,
                7,
                11,
                34,
                24,
                2,
                29,
                4,
                25,
                17
            ]
        ]
    },
    "Two_Solvers_Implied_Symmetry_On_Distances": {
        "time": 300,
        "optimal": false,
        "obj": 1126,
        "sol": [
            [
                31,
                28,
                29,
                26,
                25,
                22,
                27,
                36,
                23,
                24,
                30,
                2,
                37,
                32,
                35,
                18,
                20,
                21,
                3,
                34
            ],
            [
                33,
                1,
                38,
                47,
                44,
                39,
                46,
                45,
                19,
                40,
                41,
                42,
                43
            ],
            [
                10,
                7,
                8,
                9,
                6,
                11,
                15,
                4,
                14,
                17,
                5,
                13,
                12,
                16
            ]
        ]
    },
    "Two_Solvers_Implied_Symmetry": {
        "time": 300,
        "optimal": false,
        "obj": 994,
        "sol": [
            [
                16,
                32,
                35,
                27,
                3,
                43,
                21,
                31,
                1,
                20,
                33,
                13,
                26,
                10,
                15,
                22
            ],
            [
                38,
                40,
                8,
                28,
                44,
                6,
                42,
                47,
                37,
                45,
                39,
                36,
                41,
                46
            ],
            [
                9,
                24,
                2,
                25,
                18,
                17,
                14,
                19,
                34,
                7,
                29,
                5,
                4,
                11,
                23,
                12,
                30
            ]
        ]
    },
    "Two_Solvers_Symmetry": {
        "time": 300,
        "optimal": false,
        "obj": 1436,
        "sol": [
            [
                9,
                27,
                25,
                12,
                16,
                6,
                30,
                23,
                26,
                17,
                8,
                19,
                13,
                29,
                2,
                32,
                7,
                28,
                4,
                1,
                14,
                11
            ],
            [
                42,
                39,
                43,
                20,
                40,
                38,
                41,
                36,
                34,
                46,
                44,
                37,
                47
            ],
            [
                22,
                45,
                35,
                10,
                33,
                18,
                3,
                21,
                31,
                15,
                5,
                24
            ]
        ]
    }
}